README
cmdapp.py
setup.py
timed.py
timed.egg-info/PKG-INFO
timed.egg-info/SOURCES.txt
timed.egg-info/dependency_links.txt
timed.egg-info/entry_points.txt
timed.egg-info/not-zip-safe
timed.egg-info/top_level.txt