Metadata-Version: 1.0
Name: timed
Version: 0.13
Summary: command-line time tracking
Home-page: http://adeel.github.com/timed
Author: Adeel Ahmad Khan
Author-email: adeel2@umbc.edu
License: UNKNOWN
Platform: UNKNOWN
Classifier: Development Status :: 4 - Beta
Classifier: Environment :: Console
Classifier: License :: OSI Approved :: BSD License
Classifier: Natural Language :: English
Classifier: Operating System :: POSIX
Classifier: Topic :: Utilities
